oper8/__init__.py
oper8/__main__.py
oper8/_version.py
oper8/component.py
oper8/constants.py
oper8/controller.py
oper8/decorator.py
oper8/exceptions.py
oper8/log_format.py
oper8/managed_object.py
oper8/patch.py
oper8/patch_strategic_merge.py
oper8/reconcile.py
oper8/rollout_manager.py
oper8/session.py
oper8/setup_vcs.py
oper8/status.py
oper8/utils.py
oper8/vcs.py
oper8/verify_resources.py
oper8/version.py
oper8/cmd/__init__.py
oper8/cmd/base.py
oper8/cmd/check_heartbeat.py
oper8/cmd/run_operator_cmd.py
oper8/cmd/setup_vcs_cmd.py
oper8/config/__init__.py
oper8/config/config.py
oper8/config/config.yaml
oper8/config/config_validation.yaml
oper8/config/validation.py
oper8/dag/__init__.py
oper8/dag/completion_state.py
oper8/dag/graph.py
oper8/dag/node.py
oper8/dag/runner.py
oper8/deploy_manager/__init__.py
oper8/deploy_manager/base.py
oper8/deploy_manager/dry_run_deploy_manager.py
oper8/deploy_manager/kube_event.py
oper8/deploy_manager/openshift_deploy_manager.py
oper8/deploy_manager/owner_references.py
oper8/deploy_manager/replace_utils.py
oper8/temporary_patch/temporary_patch_component.py
oper8/temporary_patch/temporary_patch_controller.py
oper8/test_helpers/__init__.py
oper8/test_helpers/helpers.py
oper8/test_helpers/kub_mock.py
oper8/test_helpers/oper8x_helpers.py
oper8/test_helpers/pwm_helpers.py
oper8/test_helpers/data/controller.template
oper8/test_helpers/data/test_ca.crt
oper8/test_helpers/data/test_ca.key
oper8/watch_manager/__init__.py
oper8/watch_manager/base.py
oper8/watch_manager/dry_run_watch_manager.py
oper8/watch_manager/ansible_watch_manager/__init__.py
oper8/watch_manager/ansible_watch_manager/ansible_watch_manager.py
oper8/watch_manager/ansible_watch_manager/modules/k8s_application.py
oper8/watch_manager/ansible_watch_manager/modules/log_rotator.py
oper8/watch_manager/ansible_watch_manager/resources/playbook-base.yaml
oper8/watch_manager/ansible_watch_manager/resources/roles/oper8_app/defaults/main.yml
oper8-0.1.36.dist-info/licenses/LICENSE
oper8-0.1.36.dist-info/METADATA
oper8-0.1.36.dist-info/WHEEL
oper8-0.1.36.dist-info/entry_points.txt
oper8-0.1.36.dist-info/top_level.txt
oper8-0.1.36.dist-info/RECORD
